timewave/__init__.py
timewave/consumers.py
timewave/engine.py
timewave/indexedmatrix.py
timewave/producers.py
timewave/stochasticconsumer.py
timewave/stochasticproducer.py
timewave/stochasticprocess/__init__.py
timewave/stochasticprocess/base.py
timewave/stochasticprocess/gauss.py
timewave/stochasticprocess/markovchain.py
timewave/stochasticprocess/multifactor.py
timewave-0.6.dist-info/LICENSE
timewave-0.6.dist-info/METADATA
timewave-0.6.dist-info/WHEEL
timewave-0.6.dist-info/top_level.txt
timewave-0.6.dist-info/RECORD
